cnanalysis/__init__.py
cnanalysis/anovaTest.py
cnanalysis/cardinalityNrareCat.py
cnanalysis/chi_square_test.py
cnanalysis/combinedAnalysis.py
cnanalysis/correlation_mat.py
cnanalysis/descriptive_sat.py
cnanalysis/destribution_out_viz.py
cnanalysis/encoder.py
cnanalysis/winsorize.py
cnanalysis-0.1.0.dist-info/licenses/LICENSE
cnanalysis-0.1.0.dist-info/METADATA
cnanalysis-0.1.0.dist-info/WHEEL
cnanalysis-0.1.0.dist-info/top_level.txt
cnanalysis-0.1.0.dist-info/RECORD
